{
  "hash": "ebd8d0c21b178318d4888e6ed43191a3",
  "result": {
    "markdown": "---\ntitle: \"Data Visualization\"\nauthor: \"Luca Mülke\"\n---\n\nChallenge 1\n\n\n::: {.cell hash='04_data_visualization_cache/html/unnamed-chunk-1_a79bfc524759917cf223544bd17beb8b'}\n\n```{.r .cell-code}\nlibrary(ggplot2)\nlibrary(tidyverse)\ncovid_data_tbl <- read_csv(\"owid-covid-data.csv\")\n```\n\n::: {.cell-output .cell-output-stderr}\n```\n#> Rows: 311447 Columns: 67\n#> ── Column specification ────────────────────────────────────────────────────────\n#> Delimiter: \",\"\n#> chr   (4): iso_code, continent, location, tests_units\n#> dbl  (62): total_cases, new_cases, new_cases_smoothed, total_deaths, new_dea...\n#> date  (1): date\n#> \n#> ℹ Use `spec()` to retrieve the full column specification for this data.\n#> ℹ Specify the column types or set `show_col_types = FALSE` to quiet this message.\n```\n:::\n\n```{.r .cell-code}\nsubset_germany <- subset(covid_data_tbl, location == \"Germany\" | location == \"United Kingdom\" | location == \"France\" | location == \"Spain\" | location == \"United States\")\n\nggplot(subset_germany, aes(x = date, y = total_cases, color = location)) + geom_line() + theme_dark() + scale_x_date(date_labels = \"%b-%Y\", date_breaks = \"1 month\") + labs(title = \"COVID-19 confirmed cases worldwide\", subtitle = \"As of 19/04/2022\", y = \"Cumulative Cases\") + scale_y_continuous(labels = function(x) paste0(x/1000000,\"M\")) + theme(axis.text.x = element_text(angle = 45, hjust = 1, size = 6), axis.title.x=element_blank(), legend.position=\"bottom\") + scale_color_brewer(palette=\"Set1\")\n```\n\n::: {.cell-output .cell-output-stderr}\n```\n#> Warning: Removed 83 rows containing missing values (`geom_line()`).\n```\n:::\n\n::: {.cell-output-display}\n![](04_data_visualization_files/figure-html/unnamed-chunk-1-1.png){width=672}\n:::\n:::\n\n\nChallenge 2\n\n\n::: {.cell hash='04_data_visualization_cache/html/unnamed-chunk-2_35f76f04452334e81c71bf404a5533b2'}\n\n:::",
    "supporting": [],
    "filters": [
      "rmarkdown/pagebreak.lua"
    ],
    "includes": {
      "include-in-header": [
        "<link href=\"../../site_libs/pagedtable-1.1/css/pagedtable.css\" rel=\"stylesheet\" />\r\n<script src=\"../../site_libs/pagedtable-1.1/js/pagedtable.js\"></script>\r\n"
      ]
    },
    "engineDependencies": {},
    "preserve": {},
    "postProcess": true
  }
}